komis/BaseEngine.py
komis/__init__.py
komis/__main__.py
komis/cli.py
komis/engines/DialogueEngine.py
komis/engines/GayEngine.py
komis/engines/LogoEngine.py
komis/engines/ReverseDialogueEngine.py
komis/engines/SimpleTextEngine.py
komis/engines/__init__.py
komis/main.py
komis/py.typed
komis-1.1.0.dist-info/LICENSE
komis-1.1.0.dist-info/METADATA
komis-1.1.0.dist-info/WHEEL
komis-1.1.0.dist-info/entry_points.txt
komis-1.1.0.dist-info/RECORD
