Metadata-Version: 2.1
Name: komis
Version: 1.1.0
Summary: Procedural comics - change your art style without redrawing everything.
Home-page: https://github.com/ceceayo/komis
License: GNU General Public License v3
Author: Ceayo
Author-email: ceayo@duck.com
Requires-Python: >=3.11,<4
Classifier: Development Status :: 2 - Pre-Alpha
Classifier: Intended Audience :: Developers
Classifier: License :: Other/Proprietary License
Classifier: Natural Language :: English
Classifier: Operating System :: OS Independent
Classifier: Programming Language :: Python :: 3
Classifier: Programming Language :: Python :: 3.11
Classifier: Programming Language :: Python :: 3.12
Classifier: Topic :: Software Development :: Libraries
Requires-Dist: pillow (>=10.4,<11.0)
Requires-Dist: rich (>=10)
Requires-Dist: typer[all] (>=0.9.0,<0.10.0)
Project-URL: Bug Tracker, https://github.com/ceceayo/komis/issues
Project-URL: Changelog, https://github.com/ceceayo/komis/blob/main/CHANGELOG.md
Project-URL: Documentation, https://komis.readthedocs.io
Project-URL: Repository, https://github.com/ceceayo/komis
